vnp/__init__.py
vnp/bigquery.py
vnp/logger.py
vnp/secret_manager.py
vnp/storage.py
vnp-0.1.2.dist-info/METADATA
vnp-0.1.2.dist-info/WHEEL
vnp-0.1.2.dist-info/licenses/LICENSE
vnp-0.1.2.dist-info/RECORD
