Metadata-Version: 2.4
Name: vnp
Version: 0.1.2
Summary: Standard PIP Package for VNP integration apps.
Author-email: Sanu Maharjan <sanu.maharjan@vnp.de>
License-File: LICENSE
Classifier: Programming Language :: Python :: 3 :: Only
Classifier: Programming Language :: Python :: 3.12
Classifier: Programming Language :: Python :: 3.13
Requires-Python: >=3.12
Requires-Dist: google-cloud-bigquery>=3.34
Requires-Dist: google-cloud-secret-manager>=2.23.3
Requires-Dist: google-cloud-storage>=3.1
Requires-Dist: pandas>=2.2.3
Requires-Dist: pydantic>=2.11.5
